parally/__init__.py
parally/client.py
parally/server.py
parally-1.3.0.dist-info/LICENSE
parally-1.3.0.dist-info/METADATA
parally-1.3.0.dist-info/WHEEL
parally-1.3.0.dist-info/top_level.txt
parally-1.3.0.dist-info/RECORD
