Metadata-Version: 2.1
Name: parally
Version: 1.3.0
Summary: Distributed computing over networks
Home-page: https://github.com/acse-ci223/parally
Author: Chris Ioannidis
Author-email: Chris Ioannidis <chris.ioannidis23@imperial.ac.uk>
Project-URL: Homepage, https://github.com/acse-ci223/parally
Project-URL: Docs, https://acse-ci223.github.io/parally/
Project-URL: Issues, https://github.com/acse-ci223/parally/issues
Classifier: Programming Language :: Python :: 3
Classifier: License :: OSI Approved :: MIT License
Classifier: Operating System :: OS Independent
Requires-Python: >=3.10
License-File: LICENSE
